LICENSE
README.md
pyproject.toml
requirements.txt
setup.py
damelibraries/__init__.py
damelibraries.egg-info/PKG-INFO
damelibraries.egg-info/SOURCES.txt
damelibraries.egg-info/dependency_links.txt
damelibraries.egg-info/entry_points.txt
damelibraries.egg-info/not-zip-safe
damelibraries.egg-info/requires.txt
damelibraries.egg-info/top_level.txt
files/images/mapgie_in_madrid_91.jpg