Metadata-Version: 2.1
Name: damelibraries
Version: 0.1.1.post1
Summary: Learning Libraries from tests by David Arroyo MEnéndez
Home-page: http://github.com/davidam/damelibraries
Author: David Arroyo Menéndez
Author-email: David Arroyo Menéndez <davidam@gmail.com>
Maintainer-email: David Arroyo Menéndez <davidam@gmail.com>
License:                     GNU GENERAL PUBLIC LICENSE
Project-URL: Homepage, https://damelibraries.davidam.com
Project-URL: Bug Reports, https://github.com/davidam/damelibraries/issues
Project-URL: Funding, https://www.paypal.com/donate/?cmd=_donations&business=davidam%40gmail.com&currency_code=EUR&amount=10&source=url
Project-URL: Say Thanks!, https://github.com/davidam/damelibraries/wiki
Project-URL: Source, https://github.com/davidam/damelibraries/
Keywords: dame,libraries,opencv,nltk,numpy,scipy,pandas,scikit,tests,development
Classifier: Development Status :: 3 - Alpha
Classifier: Intended Audience :: Developers
Classifier: Topic :: Software Development :: Build Tools
Classifier: License :: OSI Approved :: GNU General Public License v3 (GPLv3)
Classifier: Programming Language :: Python :: 3
Classifier: Programming Language :: Python :: 3.7
Classifier: Programming Language :: Python :: 3.8
Classifier: Programming Language :: Python :: 3.9
Classifier: Programming Language :: Python :: 3.10
Classifier: Programming Language :: Python :: 3.11
Classifier: Programming Language :: Python :: 3 :: Only
Requires-Python: >=3.7
Provides-Extra: dev
Provides-Extra: test
License-File: LICENSE
